henchman/__init__.py
henchman/__main__.py
henchman/version.py
henchman/cli/__init__.py
henchman/cli/app.py
henchman/cli/console.py
henchman/cli/input.py
henchman/cli/json_output.py
henchman/cli/prompts.py
henchman/cli/repl.py
henchman/cli/repl.py.backup
henchman/cli/repl.py.backup2
henchman/cli/commands/__init__.py
henchman/cli/commands/builtins.py
henchman/cli/commands/chat.py
henchman/cli/commands/extensions.py
henchman/cli/commands/mcp.py
henchman/cli/commands/plan.py
henchman/cli/commands/rag.py
henchman/cli/commands/skill.py
henchman/cli/commands/unlimited.py
henchman/config/__init__.py
henchman/config/context.py
henchman/config/schema.py
henchman/config/settings.py
henchman/core/__init__.py
henchman/core/agent.py
henchman/core/agent.py.backup
henchman/core/events.py
henchman/core/session.py
henchman/core/turn.py
henchman/extensions/__init__.py
henchman/extensions/base.py
henchman/extensions/manager.py
henchman/mcp/__init__.py
henchman/mcp/client.py
henchman/mcp/config.py
henchman/mcp/manager.py
henchman/mcp/tool.py
henchman/providers/__init__.py
henchman/providers/anthropic.py
henchman/providers/base.py
henchman/providers/deepseek.py
henchman/providers/ollama.py
henchman/providers/openai_compat.py
henchman/providers/openai_compat.py.backup
henchman/providers/registry.py
henchman/rag/__init__.py
henchman/rag/chunker.py
henchman/rag/concurrency.py
henchman/rag/embedder.py
henchman/rag/indexer.py
henchman/rag/repo_id.py
henchman/rag/store.py
henchman/rag/system.py
henchman/skills/__init__.py
henchman/skills/executor.py
henchman/skills/learner.py
henchman/skills/models.py
henchman/skills/store.py
henchman/tools/__init__.py
henchman/tools/base.py
henchman/tools/registry.py
henchman/tools/builtins/__init__.py
henchman/tools/builtins/ask_user.py
henchman/tools/builtins/file_edit.py
henchman/tools/builtins/file_read.py
henchman/tools/builtins/file_write.py
henchman/tools/builtins/glob_tool.py
henchman/tools/builtins/grep.py
henchman/tools/builtins/ls.py
henchman_ai-0.1.11.dist-info/METADATA
henchman_ai-0.1.11.dist-info/WHEEL
henchman_ai-0.1.11.dist-info/entry_points.txt
henchman_ai-0.1.11.dist-info/licenses/LICENSE
henchman_ai-0.1.11.dist-info/RECORD
