Metadata-Version: 2.4
Name: henchman-ai
Version: 0.1.11
Summary: A model-agnostic AI agent CLI - your AI henchman for the terminal
Project-URL: Homepage, https://github.com/MGPowerlytics/henchman-ai
Project-URL: Repository, https://github.com/MGPowerlytics/henchman-ai
Project-URL: Documentation, https://github.com/MGPowerlytics/henchman-ai#readme
Author-email: Matthew <matthew@example.com>
License-Expression: MIT
License-File: LICENSE
Keywords: agent,ai,anthropic,assistant,cli,deepseek,henchman,llm,openai,terminal
Classifier: Development Status :: 4 - Beta
Classifier: Environment :: Console
Classifier: Intended Audience :: Developers
Classifier: License :: OSI Approved :: MIT License
Classifier: Operating System :: OS Independent
Classifier: Programming Language :: Python :: 3
Classifier: Programming Language :: Python :: 3.10
Classifier: Programming Language :: Python :: 3.11
Classifier: Programming Language :: Python :: 3.12
Classifier: Topic :: Software Development :: Libraries :: Python Modules
Classifier: Topic :: Utilities
Classifier: Typing :: Typed
Requires-Python: >=3.10
Requires-Dist: aiohttp>=3.9
Requires-Dist: anthropic>=0.40
Requires-Dist: anyio>=4.0
Requires-Dist: chromadb>=0.4
Requires-Dist: click>=8.0
Requires-Dist: fastembed>=0.3
Requires-Dist: httpx>=0.27
Requires-Dist: mcp>=1.0
Requires-Dist: openai>=1.40
Requires-Dist: prompt-toolkit>=3.0
Requires-Dist: pydantic>=2.0
Requires-Dist: pyyaml>=6.0
Requires-Dist: rich>=13.0
Requires-Dist: tiktoken>=0.5
Provides-Extra: dev
Requires-Dist: mypy>=1.10; extra == 'dev'
Requires-Dist: pytest-asyncio>=0.23; extra == 'dev'
Requires-Dist: pytest-cov>=4.0; extra == 'dev'
Requires-Dist: pytest>=8.0; extra == 'dev'
Requires-Dist: ruff>=0.4; extra == 'dev'
Requires-Dist: types-pyyaml>=6.0; extra == 'dev'
